Metadata-Version: 2.1
Name: logger-loco
Version: 0.1.7
Summary: Comment-driven python loggin package
Home-page: https://github.com/lushkovsky-s/logger-loco
Author: Sergey Lushkovsky
Author-email: s.lushkovsky@gmail.com
License: UNKNOWN
Keywords: logging,logger,log,comments
Platform: UNKNOWN
Classifier: Programming Language :: Python :: 3
Classifier: License :: OSI Approved :: MIT License
Classifier: Operating System :: OS Independent
Requires-Python: >=3.6
